pyramid_favicon/favicon.py
pyramid_favicon/myapp.py
pyramid_favicon/myapp2.py
pyramid_favicon/tests.py
pyramid_favicon/__init__.py
pyramid_favicon-0.0.6.dist-info/DESCRIPTION.rst
pyramid_favicon-0.0.6.dist-info/entry_points.txt
pyramid_favicon-0.0.6.dist-info/METADATA
pyramid_favicon-0.0.6.dist-info/metadata.json
pyramid_favicon-0.0.6.dist-info/RECORD
pyramid_favicon-0.0.6.dist-info/top_level.txt
pyramid_favicon-0.0.6.dist-info/WHEEL
